hihydebugaa/__init__.py
hihydebugaa/hi.hy
hihydebugaa-0.1.1.dist-info/LICENSE
hihydebugaa-0.1.1.dist-info/METADATA
hihydebugaa-0.1.1.dist-info/WHEEL
hihydebugaa-0.1.1.dist-info/top_level.txt
hihydebugaa-0.1.1.dist-info/RECORD
