Metadata-Version: 2.1
Name: hihydebugaa
Version: 0.1.1
Summary: UNKNOWN
Home-page: UNKNOWN
Author: Alex Anggada
Author-email: UNKNOWN
License: gpl-3.0
Platform: any
Requires-Dist: hy
